ppdp_anonops/__init__.py
ppdp_anonops/addition.py
ppdp_anonops/anonymizationOperationInterface.py
ppdp_anonops/condensation.py
ppdp_anonops/cryptography.py
ppdp_anonops/generalization.py
ppdp_anonops/substitution.py
ppdp_anonops/suppression.py
ppdp_anonops/swapping.py
ppdp_anonops/tests/__init__.py
ppdp_anonops/tests/test_addition.py
ppdp_anonops/tests/test_condensation.py
ppdp_anonops/tests/test_cryptography.py
ppdp_anonops/tests/test_generalization.py
ppdp_anonops/tests/test_substitution.py
ppdp_anonops/tests/test_suppression.py
ppdp_anonops/tests/test_swapping.py
ppdp_anonops/tests/test_utils_taxonomyTree.py
ppdp_anonops/utils/__init__.py
ppdp_anonops/utils/euclidClusterHelper.py
ppdp_anonops/utils/taxonomyTree.py
ppdp_anonops-0.1.1.dist-info/LICENSE
ppdp_anonops-0.1.1.dist-info/METADATA
ppdp_anonops-0.1.1.dist-info/WHEEL
ppdp_anonops-0.1.1.dist-info/top_level.txt
ppdp_anonops-0.1.1.dist-info/RECORD
